vandu/__init__.py
vandu/test2.py
vandu/vandu.py
vandu-0.0.1.dist-info/LICENSE.txt
vandu-0.0.1.dist-info/METADATA
vandu-0.0.1.dist-info/WHEEL
vandu-0.0.1.dist-info/top_level.txt
vandu-0.0.1.dist-info/RECORD
