Metadata-Version: 2.1
Name: vandu
Version: 0.0.1
Summary: beauty of vandna
Author: jam.code
Author-email: jamunaprasadyaadavrnq@gmail.com
Keywords: vandu,math,mathematics,jam.code,vandna
Classifier: Development Status :: 1 - Planning
Classifier: Intended Audience :: Developers
Classifier: Programming Language :: Python :: 3
Classifier: Operating System :: Unix
Classifier: Operating System :: MacOS :: MacOS X
Classifier: Operating System :: Microsoft :: Windows
License-File: LICENSE.txt
